[
  {
    "shortcut": "CMD+1",
    "display": "View at 100% zoom",
    "mac_sc": "⌘  1",
    "pc_sc": "—",
    "pc_safe": false,
    "difficulty": 1,
    "group": ""
  },
  {
    "shortcut": "CMD+2",
    "display": "View at 200% zoom",
    "mac_sc": "⌘  2",
    "pc_sc": "—",
    "pc_safe": false,
    "difficulty": 1,
    "group": ""
  },
  {
    "shortcut": "CMD+4",
    "display": "View at 400% zoom",
    "mac_sc": "⌘  4",
    "pc_sc": "—",
    "pc_safe": false,
    "difficulty": 1,
    "group": ""
  },
  {
    "shortcut": "V",
    "display": "Switch to the Selection tool",
    "mac_sc": "V",
    "pc_sc": "V",
    "pc_safe": true,
    "difficulty": 1,
    "group": ""
  },
  {
    "shortcut": "A",
    "display": "Switch to the Direct Selection tool",
    "mac_sc": "A",
    "pc_sc": "A",
    "pc_safe": true,
    "difficulty": 1,
    "group": ""
  },
  {
    "shortcut": "P",
    "display": "Pick up the Pen tool",
    "mac_sc": "P",
    "pc_sc": "P",
    "pc_safe": true,
    "difficulty": 1,
    "group": ""
  },
  {
    "shortcut": "B",
    "display": "Pick up the Brush tool",
    "mac_sc": "B",
    "pc_sc": "B",
    "pc_safe": true,
    "difficulty": 1,
    "group": ""
  },
  {
    "shortcut": "E",
    "display": "Switch to the Free Transform tool",
    "mac_sc": "E",
    "pc_sc": "E",
    "pc_safe": true,
    "difficulty": 3,
    "group": ""
  },
  {
    "shortcut": "T",
    "display": "Switch to the Type tool",
    "mac_sc": "T",
    "pc_sc": "T",
    "pc_safe": true,
    "difficulty": 1,
    "group": ""
  },
  {
    "shortcut": "L",
    "display": "Switch to the Ellipse tool",
    "mac_sc": "L",
    "pc_sc": "L",
    "pc_safe": true,
    "difficulty": 1,
    "group": ""
  },
  {
    "shortcut": "M",
    "display": "Switch to the Rectangle tool",
    "mac_sc": "M",
    "pc_sc": "M",
    "pc_safe": true,
    "difficulty": 1,
    "group": ""
  },
  {
    "shortcut": "I",
    "display": "Pick up the Eyedropper",
    "mac_sc": "I",
    "pc_sc": "I",
    "pc_safe": true,
    "difficulty": 1,
    "group": ""
  },
  {
    "shortcut": "Z",
    "display": "Pick up the Magnifying Glass",
    "mac_sc": "Z",
    "pc_sc": "Z",
    "pc_safe": true,
    "difficulty": 1,
    "group": ""
  },
  {
    "shortcut": "C",
    "display": "Switch to the Scissors tool",
    "mac_sc": "C",
    "pc_sc": "C",
    "pc_safe": true,
    "difficulty": 3,
    "group": ""
  },
  {
    "shortcut": "G",
    "display": "Switch to the Gradient tool",
    "mac_sc": "G",
    "pc_sc": "G",
    "pc_safe": true,
    "difficulty": 1,
    "group": ""
  },
  {
    "shortcut": "H",
    "display": "Select the Hand tool",
    "mac_sc": "H",
    "pc_sc": "H",
    "pc_safe": true,
    "difficulty": 1,
    "group": ""
  },
  {
    "shortcut": "W",
    "display": "Toggle Preview mode",
    "mac_sc": "W",
    "pc_sc": "W",
    "pc_safe": true,
    "difficulty": 3,
    "group": ""
  },
  {
    "shortcut": "D",
    "display": "Reset colours to black & white",
    "mac_sc": "D",
    "pc_sc": "D",
    "pc_safe": true,
    "difficulty": 1,
    "group": ""
  },
  {
    "shortcut": "X",
    "display": "Swap the foreground & background colours",
    "mac_sc": "X",
    "pc_sc": "X",
    "pc_safe": true,
    "difficulty": 1,
    "group": ""
  },
  {
    "shortcut": "SPACE",
    "display": "Hold to temporarily activate the Hand tool and pan",
    "mac_sc": "Space",
    "pc_sc": "Space",
    "pc_safe": true,
    "difficulty": 1,
    "group": ""
  },
  {
    "shortcut": "SHIFT",
    "display": "Hold to constrain proportions while transforming",
    "mac_sc": "⇧  Shift",
    "pc_sc": "⇧  Shift",
    "pc_safe": true,
    "difficulty": 1,
    "group": ""
  },
  {
    "shortcut": "SHIFT",
    "display": "Hold to add to an active selection",
    "mac_sc": "⇧  Shift",
    "pc_sc": "⇧  Shift",
    "pc_safe": true,
    "difficulty": 1,
    "group": ""
  },
  {
    "shortcut": "OPTION",
    "display": "Hold to transform from the centre outward",
    "mac_sc": "⌥  Option",
    "pc_sc": "Alt",
    "pc_safe": true,
    "difficulty": 1,
    "group": ""
  },
  {
    "shortcut": "TAB",
    "display": "Hide or show all panels",
    "mac_sc": "Tab",
    "pc_sc": "Tab",
    "pc_safe": true,
    "difficulty": 3,
    "group": ""
  },
  {
    "shortcut": "CMD+=",
    "display": "Zoom in",
    "mac_sc": "⌘  =",
    "pc_sc": "Ctrl =",
    "pc_safe": true,
    "difficulty": 1,
    "group": ""
  },
  {
    "shortcut": "CMD+-",
    "display": "Zoom out",
    "mac_sc": "⌘  -",
    "pc_sc": "Ctrl -",
    "pc_safe": true,
    "difficulty": 1,
    "group": ""
  },
  {
    "shortcut": "CMD+0",
    "display": "Fit the page to your screen",
    "mac_sc": "⌘  0",
    "pc_sc": "Ctrl 0",
    "pc_safe": true,
    "difficulty": 1,
    "group": ""
  },
  {
    "shortcut": "CMD+;",
    "display": "Show or hide guides",
    "mac_sc": "⌘  ;",
    "pc_sc": "Ctrl ;",
    "pc_safe": true,
    "difficulty": 1,
    "group": ""
  },
  {
    "shortcut": "CMD+OPTION+;",
    "display": "Lock or unlock all guides",
    "mac_sc": "⌘  ⌥  ;",
    "pc_sc": "Ctrl Alt ;",
    "pc_safe": true,
    "difficulty": 3,
    "group": ""
  },
  {
    "shortcut": "CMD+OPTION+I",
    "display": "Show or hide non-printing characters",
    "mac_sc": "⌘  ⌥  I",
    "pc_sc": "Ctrl Alt I",
    "pc_safe": true,
    "difficulty": 3,
    "group": ""
  },
  {
    "shortcut": "CMD+G",
    "display": "Group selected objects",
    "mac_sc": "⌘  G",
    "pc_sc": "Ctrl G",
    "pc_safe": true,
    "difficulty": 1,
    "group": ""
  },
  {
    "shortcut": "CMD+SHIFT+G",
    "display": "Ungroup selected objects",
    "mac_sc": "⌘  ⇧  G",
    "pc_sc": "Ctrl ⇧  G",
    "pc_safe": true,
    "difficulty": 3,
    "group": ""
  },
  {
    "shortcut": "CMD+]",
    "display": "Raise object one level in the stack",
    "mac_sc": "⌘  ]",
    "pc_sc": "Ctrl ]",
    "pc_safe": true,
    "difficulty": 1,
    "group": ""
  },
  {
    "shortcut": "CMD+[",
    "display": "Lower object one level in the stack",
    "mac_sc": "⌘  [",
    "pc_sc": "Ctrl [",
    "pc_safe": true,
    "difficulty": 1,
    "group": ""
  },
  {
    "shortcut": "CMD+SHIFT+A",
    "display": "Deselect all",
    "mac_sc": "⌘  ⇧  A",
    "pc_sc": "Ctrl ⇧  A",
    "pc_safe": true,
    "difficulty": 3,
    "group": ""
  },
  {
    "shortcut": "CMD+B",
    "display": "Paste in Back",
    "mac_sc": "⌘  B",
    "pc_sc": "Ctrl B",
    "pc_safe": true,
    "difficulty": 1,
    "group": ""
  },
  {
    "shortcut": "CMD+SHIFT+>",
    "display": "Increase font size",
    "mac_sc": "⌘  ⇧  >",
    "pc_sc": "Ctrl ⇧  >",
    "pc_safe": true,
    "difficulty": 3,
    "group": ""
  },
  {
    "shortcut": "CMD+SHIFT+<",
    "display": "Decrease font size",
    "mac_sc": "⌘  ⇧  <",
    "pc_sc": "Ctrl ⇧  <",
    "pc_safe": true,
    "difficulty": 3,
    "group": ""
  },
  {
    "shortcut": "CMD+SHIFT+L",
    "display": "Align text left",
    "mac_sc": "⌘  ⇧  L",
    "pc_sc": "Ctrl ⇧  L",
    "pc_safe": true,
    "difficulty": 3,
    "group": ""
  },
  {
    "shortcut": "CMD+SHIFT+C",
    "display": "Align text to centre",
    "mac_sc": "⌘  ⇧  C",
    "pc_sc": "Ctrl ⇧  C",
    "pc_safe": true,
    "difficulty": 3,
    "group": ""
  },
  {
    "shortcut": "OPTION+ARROWLEFT",
    "display": "Decrease kerning or tracking",
    "mac_sc": "⌥  ← ",
    "pc_sc": "Alt ← ",
    "pc_safe": false,
    "difficulty": 3,
    "group": ""
  },
  {
    "shortcut": "OPTION+ARROWRIGHT",
    "display": "Increase kerning or tracking",
    "mac_sc": "⌥  → ",
    "pc_sc": "Alt → ",
    "pc_safe": false,
    "difficulty": 3,
    "group": ""
  },
  {
    "shortcut": "OPTION+ARROWUP",
    "display": "Decrease leading",
    "mac_sc": "⌥  ↑ ",
    "pc_sc": "Alt ↑ ",
    "pc_safe": true,
    "difficulty": 3,
    "group": ""
  },
  {
    "shortcut": "OPTION+ARROWDOWN",
    "display": "Increase leading",
    "mac_sc": "⌥  ↓ ",
    "pc_sc": "Alt ↓ ",
    "pc_safe": true,
    "difficulty": 3,
    "group": ""
  },
  {
    "shortcut": "CMD+SHIFT+P",
    "display": "Place a file",
    "mac_sc": "⌘  ⇧  P",
    "pc_sc": "Ctrl ⇧  P",
    "pc_safe": true,
    "difficulty": 1,
    "group": ""
  },
  {
    "shortcut": "ARROWLEFT",
    "display": "Nudge selection 1px to the left",
    "mac_sc": "← ",
    "pc_sc": "← ",
    "pc_safe": true,
    "difficulty": 1,
    "group": "nudge"
  },
  {
    "shortcut": "ARROWRIGHT",
    "display": "Nudge selection 1px to the right",
    "mac_sc": "→ ",
    "pc_sc": "→ ",
    "pc_safe": true,
    "difficulty": 1,
    "group": "nudge"
  },
  {
    "shortcut": "ARROWUP",
    "display": "Nudge selection 1px upward",
    "mac_sc": "↑ ",
    "pc_sc": "↑ ",
    "pc_safe": true,
    "difficulty": 1,
    "group": "nudge"
  },
  {
    "shortcut": "ARROWDOWN",
    "display": "Nudge selection 1px downward",
    "mac_sc": "↓ ",
    "pc_sc": "↓ ",
    "pc_safe": true,
    "difficulty": 1,
    "group": "nudge"
  },
  {
    "shortcut": "SHIFT+ARROWLEFT",
    "display": "Nudge selection 10px to the left",
    "mac_sc": "⇧  ← ",
    "pc_sc": "⇧  ← ",
    "pc_safe": true,
    "difficulty": 1,
    "group": "nudge"
  },
  {
    "shortcut": "SHIFT+ARROWRIGHT",
    "display": "Nudge selection 10px to the right",
    "mac_sc": "⇧  → ",
    "pc_sc": "⇧  → ",
    "pc_safe": true,
    "difficulty": 1,
    "group": "nudge"
  },
  {
    "shortcut": "SHIFT+ARROWUP",
    "display": "Nudge selection 10px upward",
    "mac_sc": "⇧  ↑ ",
    "pc_sc": "⇧  ↑ ",
    "pc_safe": true,
    "difficulty": 1,
    "group": "nudge"
  },
  {
    "shortcut": "SHIFT+ARROWDOWN",
    "display": "Nudge selection 10px downward",
    "mac_sc": "⇧  ↓ ",
    "pc_sc": "⇧  ↓ ",
    "pc_safe": true,
    "difficulty": 1,
    "group": "nudge"
  },
  {
    "shortcut": "X",
    "display": "Swap the fill & stroke colours",
    "mac_sc": "X",
    "pc_sc": "X",
    "pc_safe": true,
    "difficulty": 1,
    "group": ""
  },
  {
    "shortcut": "OPTION",
    "display": "Hold this while you drag to duplicate",
    "mac_sc": "⌥  Option",
    "pc_sc": "Alt",
    "pc_safe": true,
    "difficulty": 3,
    "group": ""
  },
  {
    "shortcut": "CMD+R",
    "display": "Toggle Rulers",
    "mac_sc": "⌘  R",
    "pc_sc": "Ctrl R",
    "pc_safe": true,
    "difficulty": 1,
    "group": ""
  },
  {
    "shortcut": "CMD",
    "display": "Temporarily active Selection Tool while using Pen Tool",
    "mac_sc": "⌘ ",
    "pc_sc": "Ctrl",
    "pc_safe": true,
    "difficulty": 1,
    "group": ""
  },
  {
    "shortcut": "CMD+I",
    "display": "Check Spelling",
    "mac_sc": "⌘  I",
    "pc_sc": "Ctrl I",
    "pc_safe": true,
    "difficulty": 3,
    "group": ""
  },
  {
    "shortcut": "CMD+OPTION+C",
    "display": "Fit Frame to Content",
    "mac_sc": "⌘  ⌥  C",
    "pc_sc": "Ctrl Alt C",
    "pc_safe": true,
    "difficulty": 5,
    "group": ""
  },
  {
    "shortcut": "CMD+OPTION+E",
    "display": "Fit Content Proportionally",
    "mac_sc": "⌘  ⌥  E",
    "pc_sc": "Ctrl Alt E",
    "pc_safe": true,
    "difficulty": 5,
    "group": ""
  },
  {
    "shortcut": "CMD+L",
    "display": "Lock the selected object",
    "mac_sc": "⌘  L",
    "pc_sc": "Ctrl L",
    "pc_safe": true,
    "difficulty": 1,
    "group": ""
  },
  {
    "shortcut": "CMD+OPTION+L",
    "display": "Unlock all on current spread",
    "mac_sc": "⌘  ⌥  L",
    "pc_sc": "Ctrl Alt L",
    "pc_safe": true,
    "difficulty": 5,
    "group": ""
  },
  {
    "shortcut": "CMD+SHIFT+T",
    "display": "Open the Tabs panel",
    "mac_sc": "⌘  ⇧  T",
    "pc_sc": "Ctrl ⇧  T",
    "pc_safe": true,
    "difficulty": 3,
    "group": ""
  },
  {
    "shortcut": "CMD+OPTION+N",
    "display": "Create a new document with the options dialogue",
    "mac_sc": "⌘  ⌥  N",
    "pc_sc": "Ctrl Alt N",
    "pc_safe": true,
    "difficulty": 5,
    "group": ""
  },
  {
    "shortcut": "CMD+SHIFT+OPTION+D",
    "display": "Duplicate and Step",
    "mac_sc": "⌘  ⇧  ⌥  D",
    "pc_sc": "Ctrl ⇧  Alt D",
    "pc_safe": true,
    "difficulty": 5,
    "group": ""
  },
  {
    "shortcut": "CMD+ENTER",
    "display": "Quick Apply a paragraph or character style",
    "mac_sc": "⌘  ⏎ ",
    "pc_sc": "Ctrl Enter",
    "pc_safe": true,
    "difficulty": 5,
    "group": ""
  },
  {
    "shortcut": "SHIFT+F7",
    "display": "Open the Alignment panel",
    "mac_sc": "⇧  F7",
    "pc_sc": "⇧  F7",
    "pc_safe": true,
    "difficulty": 3,
    "group": ""
  },
  {
    "shortcut": "CMD+OPTION+K",
    "display": "Keep Options",
    "mac_sc": "⌘  ⌥  K",
    "pc_sc": "Ctrl Alt K",
    "pc_safe": true,
    "difficulty": 5,
    "group": ""
  },
  {
    "shortcut": "CMD+J",
    "display": "Go to a Specific Page",
    "mac_sc": "⌘  J",
    "pc_sc": "Ctrl J",
    "pc_safe": true,
    "difficulty": 5,
    "group": ""
  },
  {
    "shortcut": "CMD+SHIFT+OPTION+P",
    "display": "Package the document for print/hand-off",
    "mac_sc": "⌘  ⇧  ⌥  P",
    "pc_sc": "Ctrl ⇧  Alt P",
    "pc_safe": true,
    "difficulty": 5,
    "group": ""
  },
  {
    "shortcut": "CMD+SHIFT",
    "display": "Hold while dragging to scale frame & content together",
    "mac_sc": "⌘  ⇧ ",
    "pc_sc": "Ctrl ⇧ ",
    "pc_safe": true,
    "difficulty": 5,
    "group": ""
  },
  {
    "shortcut": "CMD+D",
    "display": "Place image",
    "mac_sc": "⌘  D",
    "pc_sc": "Ctrl D",
    "pc_safe": true,
    "difficulty": 1,
    "group": ""
  },
  {
    "shortcut": "CMD+K",
    "display": "Open Preferences",
    "mac_sc": "⌘  K",
    "pc_sc": "Ctrl K",
    "pc_safe": true,
    "difficulty": 5,
    "group": ""
  },
  {
    "shortcut": "CMD+SHIFT+OPTION+I",
    "display": "Open File Info",
    "mac_sc": "⌘  ⇧  ⌥  I",
    "pc_sc": "Ctrl ⇧  Alt I",
    "pc_safe": true,
    "difficulty": 5,
    "group": ""
  },
  {
    "shortcut": "CMD+SHIFT+V",
    "display": "Paste without Formatting",
    "mac_sc": "⌘  ⇧  V",
    "pc_sc": "Ctrl ⇧  V",
    "pc_safe": true,
    "difficulty": 1,
    "group": ""
  },
  {
    "shortcut": "CMD+OPTION+U",
    "display": "Step & Repeat",
    "mac_sc": "⌘  ⌥  U",
    "pc_sc": "Ctrl Alt U",
    "pc_safe": true,
    "difficulty": 5,
    "group": ""
  },
  {
    "shortcut": "CMD+SHIFT+PAGEUP",
    "display": "Go to First Page",
    "mac_sc": "⌘  ⇧  Page↑ ",
    "pc_sc": "Ctrl ⇧  Page Up",
    "pc_safe": true,
    "difficulty": 3,
    "group": "pages"
  },
  {
    "shortcut": "CMD+SHIFT+PAGEDOWN",
    "display": "Go to Last Page",
    "mac_sc": "⌘  ⇧  Page↓ ",
    "pc_sc": "Ctrl ⇧  Page Down",
    "pc_safe": true,
    "difficulty": 3,
    "group": "pages"
  },
  {
    "shortcut": "CMD+PAGEUP",
    "display": "Go Back",
    "mac_sc": "⌘  Page↑ ",
    "pc_sc": "Ctrl Page Up",
    "pc_safe": true,
    "difficulty": 3,
    "group": ""
  },
  {
    "shortcut": "CMD+PAGEDOWN",
    "display": "Go Forward",
    "mac_sc": "⌘  Page↓ ",
    "pc_sc": "Ctrl Page Down",
    "pc_safe": true,
    "difficulty": 3,
    "group": ""
  },
  {
    "shortcut": "SHIFT+PAGEUP",
    "display": "Got to Previous Page",
    "mac_sc": "⇧  Page↑ ",
    "pc_sc": "⇧  Page Up",
    "pc_safe": true,
    "difficulty": 3,
    "group": "pages"
  },
  {
    "shortcut": "SHIFT+PAGEDOWN",
    "display": "Got to Next Page",
    "mac_sc": "⇧  Page↓ ",
    "pc_sc": "⇧  Page Down",
    "pc_safe": true,
    "difficulty": 3,
    "group": "pages"
  },
  {
    "shortcut": "SHIFT+OPTION+P",
    "display": "Add Page",
    "mac_sc": "⇧  ⌥  P",
    "pc_sc": "⇧  Alt P",
    "pc_safe": true,
    "difficulty": 1,
    "group": ""
  },
  {
    "shortcut": "CMD+SHIFT+O",
    "display": "Create Outlines",
    "mac_sc": "⌘  ⇧  O",
    "pc_sc": "Ctrl ⇧  O",
    "pc_safe": true,
    "difficulty": 1,
    "group": ""
  },
  {
    "shortcut": "CMD+SHIFT+OPTION+O",
    "display": "Create Outlines without deleting text",
    "mac_sc": "⌘  ⇧  ⌥  O",
    "pc_sc": "Ctrl ⇧  Alt O",
    "pc_safe": true,
    "difficulty": 5,
    "group": ""
  },
  {
    "shortcut": "SHIFT+ENTER",
    "display": "Insert forced Line-Break",
    "mac_sc": "⇧  ⏎ ",
    "pc_sc": "⇧  Enter",
    "pc_safe": true,
    "difficulty": 3,
    "group": ""
  },
  {
    "shortcut": "CMD+ENTER",
    "display": "Insert Page-Break",
    "mac_sc": "⌘  ⏎ ",
    "pc_sc": "Ctrl Enter",
    "pc_safe": true,
    "difficulty": 3,
    "group": ""
  },
  {
    "shortcut": "CMD+OPTION+X",
    "display": "Insert Non-Breaking Space",
    "mac_sc": "⌘  ⌥  X",
    "pc_sc": "Ctrl Alt X",
    "pc_safe": true,
    "difficulty": 5,
    "group": ""
  },
  {
    "shortcut": "CMD+SHIFT+OPTION+T",
    "display": "Create Table",
    "mac_sc": "⌘  ⇧  ⌥  T",
    "pc_sc": "Ctrl ⇧  Alt T",
    "pc_safe": true,
    "difficulty": 3,
    "group": ""
  },
  {
    "shortcut": "CMD+OPTION+Y",
    "display": "Show Text threads",
    "mac_sc": "⌘  ⌥  Y",
    "pc_sc": "Ctrl Alt Y",
    "pc_safe": true,
    "difficulty": 5,
    "group": ""
  },
  {
    "shortcut": "CMD+SHIFT+GRAVE",
    "display": "Snap to Grid",
    "mac_sc": "⌘  ⇧  '",
    "pc_sc": "Ctrl ⇧  '",
    "pc_safe": true,
    "difficulty": 3,
    "group": ""
  },
  {
    "shortcut": "F7",
    "display": "Open Layers Panel",
    "mac_sc": "F7",
    "pc_sc": "F7",
    "pc_safe": true,
    "difficulty": 3,
    "group": ""
  },
  {
    "shortcut": "SHIFT+F6",
    "display": "Seperations Preview",
    "mac_sc": "⇧  F6",
    "pc_sc": "⇧  F6",
    "pc_safe": true,
    "difficulty": 5,
    "group": ""
  },
  {
    "shortcut": "SHIFT+OPTION+ARROWDOWN",
    "display": "Nudge Down 10px and Duplicate",
    "mac_sc": "⇧  ⌥  ↓ ",
    "pc_sc": "⇧  Alt ↓ ",
    "pc_safe": true,
    "difficulty": 1,
    "group": ""
  },
  {
    "shortcut": "SHIFT+OPTION+V",
    "display": "Resize Vertical",
    "mac_sc": "⇧  ⌥  V",
    "pc_sc": "⇧  Alt V",
    "pc_safe": true,
    "difficulty": 5,
    "group": ""
  },
  {
    "shortcut": "CMD+OPTION+ARROWUP",
    "display": "Pin Top Edge",
    "mac_sc": "⌘  ⌥  ↑ ",
    "pc_sc": "Ctrl Alt ↑ ",
    "pc_safe": true,
    "difficulty": 5,
    "group": ""
  },
  {
    "shortcut": "CMD+OPTION+G",
    "display": "Select All Guides",
    "mac_sc": "⌘  ⌥  G",
    "pc_sc": "Ctrl Alt G",
    "pc_safe": true,
    "difficulty": 5,
    "group": ""
  },
  {
    "shortcut": "CMD+SHIFT+OPTION+L",
    "display": "Override All Master Page",
    "mac_sc": "⌘  ⇧  ⌥  L",
    "pc_sc": "Ctrl ⇧  Alt L",
    "pc_safe": true,
    "difficulty": 5,
    "group": ""
  },
  {
    "shortcut": "=",
    "display": "Add Anchor Point",
    "mac_sc": "=",
    "pc_sc": "=",
    "pc_safe": true,
    "difficulty": 5,
    "group": ""
  },
  {
    "shortcut": "SHIFT+T",
    "display": "Type on a Path Tool",
    "mac_sc": "⇧  T",
    "pc_sc": "⇧  T",
    "pc_safe": true,
    "difficulty": 3,
    "group": ""
  }
]